{"version":1,"resource":"file:///var/www/html/school/S3/project/app/controleur/CreerUnCommentaire.php","entries":[{"id":"M3cx.php","timestamp":1731429959502},{"id":"gQQr.php","timestamp":1731429974593},{"id":"EVst.php","timestamp":1731430014320},{"id":"OuiC.php","source":"undoRedo.source","timestamp":1731430015355},{"id":"YW6Y.php","timestamp":1731430047245},{"id":"d6LA.php","timestamp":1731430070282},{"id":"IwJ5.php","timestamp":1731430247255},{"id":"HCMx.php","source":"renamed.source","sourceDescription":"/var/www/html/school/S3/project/app/controleur/AjouterUnCommentaire.php","timestamp":1731430371557},{"id":"VNBr.php","timestamp":1731430375615},{"id":"ERfJ.php","timestamp":1731430386573},{"id":"YseQ.php","timestamp":1731664809446},{"id":"QssI.php","timestamp":1731665588203},{"id":"nTNI.php","source":"searchReplace.source","timestamp":1731665642985},{"id":"bNwu.php","timestamp":1731665659878},{"id":"crrP.php","source":"searchReplace.source","timestamp":1731665686700},{"id":"MhYN.php","timestamp":1731665698135},{"id":"YVmH.php","source":"undoRedo.source","timestamp":1731665715690},{"id":"bnv5.php","timestamp":1731665760745},{"id":"L3cd.php","timestamp":1731665824742},{"id":"5lHg.php","timestamp":1731665902992},{"id":"aiNl.php","timestamp":1731665942099},{"id":"htu5.php","source":"undoRedo.source","timestamp":1731665951121},{"id":"0ZUJ.php","timestamp":1731665983706},{"id":"SORt.php","timestamp":1731665998101},{"id":"dAo7.php","timestamp":1731666017552},{"id":"eQYg.php","timestamp":1731668272738}]}