{"version":1,"resource":"file:///home/angus/Documents/work/S3/sae3a01/app/src/main/java/dao/ChargesDAO.java","entries":[{"id":"V3v8.java","timestamp":1732525295297},{"id":"UO1P.java","source":"undoRedo.source","timestamp":1732525299189},{"id":"BGQf.java","timestamp":1732525339889},{"id":"Db8J.java","timestamp":1732525439983},{"id":"nA2F.java","timestamp":1732525809693},{"id":"U7bI.java","timestamp":1732525912619},{"id":"ziQ0.java","timestamp":1732525935271},{"id":"Kkt6.java","source":"undoRedo.source","timestamp":1732525937404},{"id":"WFng.java","timestamp":1732526000978},{"id":"iBtN.java","source":"Workspace Edit","timestamp":1732534740942},{"id":"4mLg.java","timestamp":1732535171208},{"id":"E1SV.java","timestamp":1732536566753},{"id":"nIrw.java","source":"Workspace Edit","timestamp":1732892529175},{"id":"3U94.java","timestamp":1732892554389},{"id":"93Qa.java","timestamp":1732892567172},{"id":"qPKE.java","source":"Renaming idBienLouable to inParent","timestamp":1732893301710},{"id":"WiKL.java","timestamp":1732893311222},{"id":"PaF7.java","source":"undoRedo.source","timestamp":1732893313571},{"id":"0OI6.java","source":"Add unimplemented methods","timestamp":1732893315746},{"id":"epPL.java","source":"Renaming idBienLouable to inParent","timestamp":1732893337588},{"id":"cLMj.java","timestamp":1732893357254},{"id":"fBVI.java","timestamp":1732893458679},{"id":"htJ0.java","timestamp":1732893544111},{"id":"qxmn.java","timestamp":1733122807333},{"id":"o8gg.java","timestamp":1733122827816},{"id":"4JOb.java","timestamp":1733122858681},{"id":"9Ejd.java","source":"undoRedo.source","timestamp":1733122870011},{"id":"wbuo.java","timestamp":1733122876257},{"id":"CBVv.java","timestamp":1733122939141},{"id":"PxJN.java","timestamp":1733123516618},{"id":"cf3i.java","source":"undoRedo.source","timestamp":1733123518151},{"id":"6aeJ.java","timestamp":1733123519391},{"id":"OsCz.java","source":"undoRedo.source","timestamp":1733123559683},{"id":"7BOb.java","timestamp":1733123618376},{"id":"S3IT.java","timestamp":1733492536864},{"id":"w9sv.java","source":"Renaming inParent to idBienLouable","timestamp":1733492541374},{"id":"wJMk.java","source":"undoRedo.source","timestamp":1733492546382},{"id":"EVc5.java","timestamp":1733492568987},{"id":"4XeD.java","timestamp":1734701109313},{"id":"avSk.java","timestamp":1734701126012},{"id":"SmwR.java","timestamp":1734701467973},{"id":"1jZ9.java","timestamp":1734701483157},{"id":"iCiy.java","timestamp":1734701546267},{"id":"zPWc.java","timestamp":1734701571555},{"id":"P8pV.java","timestamp":1734701592199},{"id":"V9fU.java","timestamp":1734702545247},{"id":"OnUu.java","timestamp":1734702569387},{"id":"QoVY.java","timestamp":1734702595758},{"id":"305P.java","timestamp":1734702743803},{"id":"9jQU.java","timestamp":1734703328680}]}