{"version":1,"resource":"file:///home/angus/Documents/perso/SvelteShine/src/code.css","entries":[{"id":"pKWE.css","timestamp":1723803138859},{"id":"KX2N.css","timestamp":1723970023345},{"id":"PJps.css","timestamp":1723970071253},{"id":"T6XI.css","timestamp":1723970124764},{"id":"o6l5.css","timestamp":1723970285988},{"id":"6sU2.css","timestamp":1723994779745},{"id":"BIUl.css","timestamp":1723995612603},{"id":"gM23.css","timestamp":1723995638091},{"id":"py8I.css","timestamp":1724184635311},{"id":"ylx8.css","source":"undoRedo.source","timestamp":1724184641729},{"id":"mGJ5.css","timestamp":1724184670308},{"id":"1y4n.css","timestamp":1724576265194},{"id":"LozQ.css","source":"Renaming step to codeStep","timestamp":1724576587766},{"id":"MA0E.css","source":"searchReplace.source","timestamp":1724593924202},{"id":"gs7i.css","timestamp":1724594544485},{"id":"cUdL.css","timestamp":1724594569584},{"id":"nKjR.css","timestamp":1724594882941},{"id":"AuWg.css","timestamp":1724594903369},{"id":"VQAl.css","timestamp":1724594916567},{"id":"gRFA.css","timestamp":1724665924755},{"id":"6t9E.css","timestamp":1724779090267},{"id":"dQsd.css","source":"undoRedo.source","timestamp":1724779096841},{"id":"erTV.css","timestamp":1724779116954},{"id":"XYBQ.css","timestamp":1724779909978},{"id":"gVWj.css","timestamp":1724779935861},{"id":"40eU.css","timestamp":1724779981913},{"id":"2hxn.css","timestamp":1724779992759},{"id":"fSFy.css","timestamp":1724780029383},{"id":"JycA.css","timestamp":1724782856253},{"id":"ArLT.css","timestamp":1724782982727},{"id":"C6Nk.css","timestamp":1724782995422},{"id":"BkCm.css","timestamp":1724783025469},{"id":"fzHf.css","source":"undoRedo.source","timestamp":1724783403389},{"id":"e6Nh.css","timestamp":1724783596420},{"id":"ULhM.css","timestamp":1724784412633},{"id":"Z3I6.css","timestamp":1724785055077},{"id":"FVtl.css","timestamp":1724787901114},{"id":"yoXc.css","timestamp":1724788098482},{"id":"i3XM.css","timestamp":1724788125224},{"id":"YyE1.css","timestamp":1724788187265},{"id":"HYbh.css","timestamp":1724799238830},{"id":"kDnH.css","source":"undoRedo.source","timestamp":1724799252418},{"id":"prOK.css","timestamp":1724799265018},{"id":"2tbm.css","source":"undoRedo.source","timestamp":1724799270802},{"id":"QjCj.css","timestamp":1724799337922},{"id":"IDgj.css","timestamp":1724799399081},{"id":"Pg32.css","timestamp":1724799428697},{"id":"nn06.css","timestamp":1724799467339},{"id":"Qg04.css","timestamp":1725537809478},{"id":"048F.css","timestamp":1725980892407}]}