{"version":1,"resource":"file:///home/angus/Documents/perso/ui/src/routes/api/note/list/addItem/%2Bserver.ts","entries":[{"id":"jyca.ts","timestamp":1737393098535},{"id":"JZIW.ts","timestamp":1737393111836},{"id":"YUwx.ts","timestamp":1737393144786},{"id":"AZr1.ts","timestamp":1737393157829},{"id":"NrBH.ts","timestamp":1737393558127},{"id":"cYXy.ts","source":"Add import from \"$lib/server/db/note\"","timestamp":1737393560427},{"id":"jtNj.ts","timestamp":1737393576113},{"id":"bgHa.ts","source":"Workspace Edit","timestamp":1737393577736},{"id":"yb34.ts","timestamp":1737393583867},{"id":"81Fe.ts","timestamp":1737394755996},{"id":"X6ot.ts","source":"moved.source","sourceDescription":"~/Documents/perso/ui/src/routes/api/note/addItem/+server.ts","timestamp":1737394773246}]}