{"version":1,"resource":"file:///home/angus/Documents/perso/my-exercise-platform/src/routes/app/exercises/%2Bpage.svelte","entries":[{"id":"lTIy.svelte","timestamp":1729096472185},{"id":"kIGG.svelte","timestamp":1729096503624},{"id":"jR82.svelte","timestamp":1729109807491},{"id":"a3hq.svelte","timestamp":1729109824517},{"id":"X1S3.svelte","timestamp":1729109834866},{"id":"fnze.svelte","timestamp":1729109885394},{"id":"FiWf.svelte","timestamp":1729109961015},{"id":"6Rit.svelte","timestamp":1729109977669},{"id":"1wvq.svelte","timestamp":1729109988975},{"id":"735s.svelte","timestamp":1729110001145},{"id":"Hb0L.svelte","timestamp":1729110034851},{"id":"ctPC.svelte","timestamp":1729110354036},{"id":"sxd8.svelte","timestamp":1729110372696},{"id":"GuCT.svelte","timestamp":1729110400745},{"id":"EPL5.svelte","timestamp":1729110680446},{"id":"YzoB.svelte","timestamp":1729110730343},{"id":"nBXE.svelte","timestamp":1729110745151},{"id":"fgvY.svelte","timestamp":1729114911002},{"id":"0W3R.svelte","timestamp":1729114962717},{"id":"c6U0.svelte","timestamp":1729151491708},{"id":"yu4m.svelte","timestamp":1729156819255},{"id":"69uK.svelte","timestamp":1729156858894},{"id":"seYI.svelte","source":"undoRedo.source","timestamp":1729156874308},{"id":"NgLI.svelte","timestamp":1729156889892},{"id":"58ek.svelte","timestamp":1729156925302},{"id":"inZC.svelte","timestamp":1729157204067},{"id":"SpM4.svelte","timestamp":1729174466600}]}