{"version":1,"resource":"file:///home/angus/Documents/perso/my-exercise-platform/src/lib/codeHighlighter.js","entries":[{"id":"mQq9.js","timestamp":1729153681048},{"id":"cdio.js","timestamp":1729153738220},{"id":"8VSx.js","source":"moved.source","sourceDescription":"~/Documents/perso/SvelteShine/src/lib/codeHighlighter copy.js","timestamp":1729153797382},{"id":"ocqS.js","source":"renamed.source","sourceDescription":"~/Documents/perso/my-exercise-platform/src/lib/codeHighlighter copy.js","timestamp":1729153804268},{"id":"ReYH.js","timestamp":1729154764554},{"id":"gGYT.js","source":"undoRedo.source","timestamp":1729154775656},{"id":"hMJj.js","timestamp":1729154779837},{"id":"xXVB.js","timestamp":1729155266861},{"id":"1y0t.js","timestamp":1729155338339}]}