{"version":1,"resource":"file:///home/angus/Documents/perso/ownlogs/ownlogs/frontend/src/hooks.server.ts","entries":[{"id":"TbtX.ts","timestamp":1733658709869},{"id":"3r9h.ts","timestamp":1733672686152},{"id":"SuA7.ts","timestamp":1733673807441},{"id":"5eiY.ts","timestamp":1733673923470},{"id":"YTPU.ts","timestamp":1733674011115},{"id":"GSSm.ts","timestamp":1733674022433},{"id":"tAHr.ts","timestamp":1733925413843},{"id":"eyNO.ts","timestamp":1733925426974},{"id":"SPhl.ts","timestamp":1733932129803},{"id":"MXvh.ts","timestamp":1733933808717},{"id":"X6Md.ts","timestamp":1733942726388},{"id":"l2Ny.ts","timestamp":1733943817740},{"id":"8bPK.ts","timestamp":1733947270716},{"id":"gS7s.ts","timestamp":1733950574668},{"id":"JLCx.ts","timestamp":1733952299473},{"id":"v1Ij.ts","timestamp":1733954725186},{"id":"kc4F.ts","timestamp":1733954982914},{"id":"amRd.ts","timestamp":1735907554692}]}