{"version":1,"resource":"file:///home/angus/Documents/perso/SvelteShine/src/lib/components/Commands.svelte","entries":[{"id":"xHAn.svelte","timestamp":1723732716335},{"id":"9UN7.svelte","source":"searchReplace.source","timestamp":1723733872822},{"id":"Mnts.svelte","timestamp":1723806127239},{"id":"nkYA.svelte","timestamp":1723970550547},{"id":"bTXm.svelte","timestamp":1723998939928},{"id":"zYFX.svelte","timestamp":1723998990367},{"id":"5U3K.svelte","timestamp":1724184703946},{"id":"sJgu.svelte","timestamp":1724184775868},{"id":"dO9G.svelte","timestamp":1724184815895},{"id":"jLXn.svelte","timestamp":1724184831241},{"id":"Cd7O.svelte","timestamp":1724184868459},{"id":"JpWi.svelte","timestamp":1724184946763},{"id":"b5Zn.svelte","timestamp":1724498544832},{"id":"TIOF.svelte","timestamp":1724498566546},{"id":"DM2X.svelte","timestamp":1724498576965},{"id":"r9FS.svelte","timestamp":1724574391543},{"id":"ScTl.svelte","timestamp":1724574476625},{"id":"SjJA.svelte","timestamp":1724574519084},{"id":"FlHH.svelte","timestamp":1724574649750},{"id":"7qeS.svelte","timestamp":1724574678306},{"id":"esoU.svelte","timestamp":1724574688759},{"id":"LogA.svelte","timestamp":1724574754568},{"id":"rxm6.svelte","timestamp":1724574774503},{"id":"jmQS.svelte","timestamp":1724574802476},{"id":"lkJf.svelte","timestamp":1724574878401},{"id":"GWW6.svelte","timestamp":1724574890000},{"id":"3UGh.svelte","timestamp":1724574909796},{"id":"1IU2.svelte","timestamp":1724574936496},{"id":"9lWf.svelte","timestamp":1724574966530},{"id":"hrfN.svelte","source":"undoRedo.source","timestamp":1724574972700},{"id":"2BaJ.svelte","timestamp":1724574980455},{"id":"iU8Z.svelte","timestamp":1724575063689},{"id":"C4sg.svelte","timestamp":1724575085659},{"id":"Z6Rr.svelte","timestamp":1724575148437},{"id":"F6mz.svelte","timestamp":1724575174570},{"id":"JP6n.svelte","source":"searchReplace.source","timestamp":1724593923439},{"id":"gJIa.svelte","timestamp":1724594773867},{"id":"LJBZ.svelte","timestamp":1724660914862},{"id":"5uE1.svelte","timestamp":1724661366634},{"id":"TG1q.svelte","timestamp":1724786357536},{"id":"7mrB.svelte","timestamp":1724786372248},{"id":"nZKB.svelte","timestamp":1724791193826},{"id":"pGbK.svelte","timestamp":1724835998512},{"id":"kLQr.svelte","source":"undoRedo.source","timestamp":1724836005671},{"id":"g9qF.svelte","timestamp":1724836049845},{"id":"HfJq.svelte","timestamp":1724836098227},{"id":"mbGu.svelte","timestamp":1724836124816},{"id":"53Y6.svelte","timestamp":1727469621717}]}