{"version":1,"resource":"file:///home/angus/Documents/perso/ui/src/routes/%5Busername%3Dusername%5D/%2Bpage.svelte","entries":[{"id":"RsQV.svelte","timestamp":1737315524483},{"id":"3uYQ.svelte","timestamp":1737316105337},{"id":"rr05.svelte","source":"undoRedo.source","timestamp":1737316106773},{"id":"tH66.svelte","source":"Add import from \"$lib/components\"","timestamp":1737316108703},{"id":"53eY.svelte","timestamp":1737316115705},{"id":"1qRG.svelte","timestamp":1737316198032},{"id":"vh9g.svelte","timestamp":1737316222233},{"id":"Pbys.svelte","source":"Update import from \"$lib/components\"","timestamp":1737316225781},{"id":"Ek89.svelte","timestamp":1737316256288},{"id":"R0aK.svelte","timestamp":1737316268529},{"id":"2B2z.svelte","timestamp":1737316330825},{"id":"667e.svelte","timestamp":1737316357811},{"id":"yFwm.svelte","timestamp":1737316436479},{"id":"YQD2.svelte","timestamp":1737316453116},{"id":"IY59.svelte","timestamp":1737316561952},{"id":"VxiT.svelte","timestamp":1737316613187},{"id":"D38p.svelte","timestamp":1737316795932},{"id":"M29c.svelte","timestamp":1737316810022},{"id":"WbER.svelte","source":"Add import from \"$app/forms\"","timestamp":1737316811558},{"id":"9K9Z.svelte","timestamp":1737316813188},{"id":"hEIl.svelte","timestamp":1737316888280},{"id":"rtgv.svelte","timestamp":1737316920985},{"id":"axJp.svelte","source":"undoRedo.source","timestamp":1737316926135},{"id":"K69u.svelte","timestamp":1737316932976},{"id":"FAl5.svelte","timestamp":1737316984220},{"id":"AoRG.svelte","timestamp":1737364920810},{"id":"IYDU.svelte","timestamp":1737364933644},{"id":"9wq7.svelte","timestamp":1737364959230},{"id":"NNWk.svelte","timestamp":1737364978941},{"id":"DGnY.svelte","timestamp":1737365001212},{"id":"0Jgf.svelte","timestamp":1737365063811},{"id":"FHRe.svelte","timestamp":1737365097137},{"id":"5AvL.svelte","timestamp":1737365160596},{"id":"o1Ln.svelte","timestamp":1737365288891},{"id":"EjF2.svelte","timestamp":1737365366814},{"id":"Ao0G.svelte","timestamp":1737365635794},{"id":"TQAJ.svelte","timestamp":1737365665196},{"id":"v7TK.svelte","source":"undoRedo.source","timestamp":1737365672152},{"id":"cN85.svelte","timestamp":1737365674217},{"id":"zqOe.svelte","timestamp":1737366045577}]}