{"version":1,"resource":"file:///home/angus/Documents/perso/ownlogs/ownlogs/frontend/src/lib/components/app-sidebar.svelte","entries":[{"id":"hOgV.svelte","timestamp":1733582448504},{"id":"YIhB.svelte","timestamp":1733658774351},{"id":"DeCj.svelte","timestamp":1733675166794},{"id":"L8zi.svelte","source":"Renaming mode to theme","timestamp":1733675174372},{"id":"p94W.svelte","timestamp":1733675177936},{"id":"bRT7.svelte","source":"undoRedo.source","timestamp":1733675756527},{"id":"K233.svelte","timestamp":1733952197608},{"id":"bILX.svelte","timestamp":1733952252331},{"id":"Uzbq.svelte","timestamp":1733955747943}]}